Metadata-Version: 2.4
Name: CodeMetaPy
Version: 3.0.3
Summary: Generate and manage CodeMeta software metadata
Home-page: https://github.com/proycon/codemetapy
Author: Maarten van Gompel
Author-email: proycon@anaproy.nl
License: GPL-3.0-only
Keywords: software metadata,codemeta,schema.org,rdf,linked data
Classifier: Development Status :: 5 - Production/Stable
Classifier: Topic :: Software Development
Classifier: Programming Language :: Python :: 3.6
Classifier: Programming Language :: Python :: 3.7
Classifier: Programming Language :: Python :: 3.8
Classifier: Programming Language :: Python :: 3.9
Classifier: Programming Language :: Python :: 3.10
Classifier: Programming Language :: Python :: 3.11
Classifier: Programming Language :: Python :: 3.12
Classifier: Programming Language :: Python :: 3.13
Classifier: Operating System :: POSIX
Classifier: Intended Audience :: Developers
Classifier: License :: OSI Approved :: GNU General Public License v3 (GPLv3)
License-File: COPYING
Requires-Dist: nameparser
Requires-Dist: importlib_metadata
Requires-Dist: BeautifulSoup4
Requires-Dist: rdflib>=6.1.1
Requires-Dist: pyshacl==0.20.0
Requires-Dist: requests
Requires-Dist: lxml
Requires-Dist: pyyaml
Requires-Dist: pep517
Requires-Dist: tomlkit
Requires-Dist: pyproject_parser
Requires-Dist: setuptools
Dynamic: author
Dynamic: author-email
Dynamic: classifier
Dynamic: description
Dynamic: description-content-type
Dynamic: home-page
Dynamic: keywords
Dynamic: license
Dynamic: license-file
Dynamic: requires-dist
Dynamic: summary
